efficientnet_3D/__init__.py
efficientnet_3D/__version__.py
efficientnet_3D/keras.py
efficientnet_3D/model.py
efficientnet_3D/preprocessing.py
efficientnet_3D/tfkeras.py
efficientnet_3D/weights.py
efficientnet_3D-1.0.2.dist-info/LICENSE
efficientnet_3D-1.0.2.dist-info/METADATA
efficientnet_3D-1.0.2.dist-info/WHEEL
efficientnet_3D-1.0.2.dist-info/top_level.txt
efficientnet_3D-1.0.2.dist-info/RECORD
