Metadata-Version: 2.1
Name: efficientnet-3D
Version: 1.0.2
Summary: EfficientNet models in 3D variant for keras and TF.keras
Home-page: https://github.com/ZFTurbo/efficientnet_3D
Author: Roman Sol (ZFTurbo)
Author-email: UNKNOWN
License: UNKNOWN
Platform: UNKNOWN
